pynbody-2.4.1.dist-info/RECORD
pynbody-2.4.1.dist-info/WHEEL
pynbody-2.4.1.dist-info/top_level.txt
pynbody-2.4.1.dist-info/METADATA
pynbody/simdict.py
pynbody/transformation.py
pynbody/configuration.py
pynbody/dependencytracker.py
pynbody/default_config.ini
pynbody/units.py
pynbody/__init__.py
pynbody/family.py
pynbody/openmp.cpython-313-darwin.so
pynbody/derived.py
pynbody/kdtree/pq.h
pynbody/kdtree/smooth.h
pynbody/kdtree/smooth.cpp
pynbody/kdtree/__init__.py
pynbody/kdtree/kdmain.cpp
pynbody/kdtree/kd.cpp
pynbody/kdtree/kdmain.cpython-313-darwin.so
pynbody/kdtree/kd.h
pynbody/snapshot/nchilada.py
pynbody/snapshot/copy_on_access.py
pynbody/snapshot/subsnap.py
pynbody/snapshot/util.py
pynbody/snapshot/ascii.py
pynbody/snapshot/__init__.py
pynbody/snapshot/simsnap.py
pynbody/snapshot/swift.py
pynbody/snapshot/tipsy.py
pynbody/snapshot/grafic.py
pynbody/snapshot/gadget.py
pynbody/snapshot/namemapper.py
pynbody/snapshot/pkdgravhdf.py
pynbody/snapshot/ramses.py
pynbody/snapshot/gadgethdf.py
pynbody/analysis/CAMB_Planck18
pynbody/analysis/CAMB_WMAP7
pynbody/analysis/default_ssp.txt
pynbody/analysis/hifrac.py
pynbody/analysis/lsst_ssp.txt
pynbody/analysis/ionfracs.npz
pynbody/analysis/ramses_util.py
pynbody/analysis/theoretical_profiles.py
pynbody/analysis/profile.py
pynbody/analysis/ionfrac.py
pynbody/analysis/angmom.py
pynbody/analysis/__init__.py
pynbody/analysis/_com.pyx
pynbody/analysis/luminosity.py
pynbody/analysis/morphology.py
pynbody/analysis/hmf.py
pynbody/analysis/_com.cpython-313-darwin.so
pynbody/analysis/halo.py
pynbody/analysis/cambtemplate.ini
pynbody/analysis/cosmology.py
pynbody/analysis/h1.hdf5
pynbody/analysis/cmdlum.npz
pynbody/gravity/_gravity.pyx
pynbody/gravity/__init__.py
pynbody/gravity/_gravity.cpython-313-darwin.so
pynbody/plot/gas.py
pynbody/plot/util.py
pynbody/plot/profile.py
pynbody/plot/generic.py
pynbody/plot/__init__.py
pynbody/plot/tollerud2008mw
pynbody/plot/stars.py
pynbody/plot/sph.py
pynbody/chunk/__init__.py
pynbody/chunk/scan.cpython-313-darwin.so
pynbody/chunk/scan.pyx
