Metadata-Version: 2.4
Name: pynbody
Version: 2.4.1
Summary: Astronomical N-body/SPH analysis for python
Author-email: The pynbody team <pynbody-users@googlegroups.com>
Project-URL: Homepage, https://github.com/pynbody/pynbody/releases
Classifier: Development Status :: 5 - Production/Stable
Classifier: Intended Audience :: Developers
Classifier: Intended Audience :: Science/Research
Classifier: License :: OSI Approved :: GNU General Public License v3 or later (GPLv3+)
Classifier: Programming Language :: Python :: 3
Classifier: Topic :: Scientific/Engineering :: Astronomy
Classifier: Topic :: Scientific/Engineering :: Visualization
Requires-Python: >=3.11
Requires-Dist: h5py>=3.8.0
Requires-Dist: matplotlib>=3.8.0
Requires-Dist: numpy>=1.26.0
Requires-Dist: scipy>=1.12.0
Requires-Dist: osfclient
Provides-Extra: tests
Requires-Dist: pytest; extra == "tests"
Requires-Dist: pandas; extra == "tests"
Requires-Dist: camb; extra == "tests"
Requires-Dist: IPython; extra == "tests"
Requires-Dist: healpy; (platform_system != "Windows" and python_version < "3.14") and extra == "tests"
Provides-Extra: docs
Requires-Dist: ipython>=3; extra == "docs"
Requires-Dist: Sphinx<8.2.0,>=7; extra == "docs"
Requires-Dist: sphinx-book-theme; extra == "docs"
Requires-Dist: sphinx-copybutton; extra == "docs"
Requires-Dist: numpydoc; extra == "docs"
Requires-Dist: nbsphinx; extra == "docs"
Requires-Dist: camb; extra == "docs"
Requires-Dist: healpy; extra == "docs"
